datastore_client/__init__.py
datastore_client/client.py
datastore_client/mock_client.py
datastore_client/utils.py
datastore_client-0.0.10.dist-info/METADATA
datastore_client-0.0.10.dist-info/WHEEL
datastore_client-0.0.10.dist-info/RECORD
