Metadata-Version: 2.1
Name: datastore-client
Version: 0.0.10
Summary: A simple Google DataStore client
Home-page: https://github.com/Flickswitch/datastore-client
Author: Jethro Muller
Author-email: git@jethromuller.co.za
Requires-Python: >=3.6,<4.0
Classifier: Programming Language :: Python :: 3
Classifier: Programming Language :: Python :: 3.6
Classifier: Programming Language :: Python :: 3.7
Classifier: Programming Language :: Python :: 3.8
Classifier: Programming Language :: Python :: 3.9
Classifier: Programming Language :: Python :: 3.10
Classifier: Programming Language :: Python :: 3.11
Requires-Dist: google-cloud-datastore (>=1.9,<3.0)
Requires-Dist: grpcio (>=1.43.0,<2.0.0)
Project-URL: Repository, https://github.com/Flickswitch/datastore-client
